[
    {
        "id": 1,
        "surah": "Surah Al Fatihah",
        "revelation": "The Opening - Revealed in Makkah",
        "ayah": "بِسْمِ ٱللَّهِ ٱلرَّحْمَـٰنِ ٱلرَّحِيمِ",
        "translation": "With the name of Allah, the extremely loving and caring right now, the always loving and caring"
    },
    {
        "id": 2,
        "surah": "Surah Al Fatihah",
        "revelation": "The Opening - Revealed in Makkah",
        "ayah": "ٱلْحَمْدُ لِلَّهِ رَبِّ ٱلْعَـٰلَمِينَ",
        "translation": "All praise and thanks is for Allah The Master of all nations and people"
    }
]
